OneGen/__init__.py
OneGen/example.py
OneGen/onegen.py
OneGen-0.0.1.dist-info/License.txt
OneGen-0.0.1.dist-info/METADATA
OneGen-0.0.1.dist-info/WHEEL
OneGen-0.0.1.dist-info/top_level.txt
OneGen-0.0.1.dist-info/RECORD
