Metadata-Version: 2.1
Name: OneGen
Version: 0.0.1
Summary: OneGen是基于pytorch的深度学习项目的快速构建
Author-email: Charles Zhu <ion_uig@163.com>
Maintainer-email: Charles Zhu <ion_uig@163.com>
Keywords: Deep Learning,Pytorch, Build Tools
Classifier: Development Status :: 3 - Alpha
Classifier: Intended Audience :: Developers
Classifier: Topic :: Software Development :: Build Tools  
Classifier: Programming Language :: Python
Requires-Python: >=3.6
License-File: License.txt
Requires-Dist: tqdm
Requires-Dist: transformer
